owasp_zap_historic_parser/__init__.py
owasp_zap_historic_parser/owasp_zap_historical.py
owasp_zap_historic_parser/runner.py
test/__init__.py
test/db_test.py
test/function_test.py
test/runner_test.py
test/test_files/__init__.py
owasp_zap_historic_parser-0.2.4.dist-info/LICENSE
owasp_zap_historic_parser-0.2.4.dist-info/METADATA
owasp_zap_historic_parser-0.2.4.dist-info/WHEEL
owasp_zap_historic_parser-0.2.4.dist-info/entry_points.txt
owasp_zap_historic_parser-0.2.4.dist-info/top_level.txt
owasp_zap_historic_parser-0.2.4.dist-info/RECORD
