Metadata-Version: 2.1
Name: owasp-zap-historic-parser
Version: 0.2.4
Summary: Parser to push OWASP ZAP report data to MySQL and generate delta report
Home-page: https://github.com/Accruent/owasp-zap-historic-parser
Author: Neil Howell
Author-email: neiljhowell@gmail.com
License: GPL-3.0
Keywords: owasp zap historical report parser
Classifier: Programming Language :: Python
Classifier: Topic :: Software Development :: Testing
License-File: LICENSE
Requires-Dist: setuptools ~=69.0.3
Requires-Dist: lxml ~=4.9.3
Requires-Dist: pytz ~=2022.7
Requires-Dist: pytest-cov ~=4.1.0
Requires-Dist: mysql-connector ~=2.2.9
Requires-Dist: SQLAlchemy ~=2.0.25
